tests/__init__.py
tests/test_cli.py
translator/__init__.py
translator/agent.py
translator/cli.py
translator/config.py
y_translator_cli-0.1.3.dist-info/licenses/LICENSE
y_translator_cli-0.1.3.dist-info/METADATA
y_translator_cli-0.1.3.dist-info/WHEEL
y_translator_cli-0.1.3.dist-info/entry_points.txt
y_translator_cli-0.1.3.dist-info/top_level.txt
y_translator_cli-0.1.3.dist-info/RECORD
